{
  "minecraft:recipes/tools/fishing_rod": {
    "criteria": {
      "has_string": "2020-03-30 02:11:55 +0530"
    },
    "done": true
  },
  "minecraft:recipes/food/cooked_mutton_from_campfire_cooking": {
    "criteria": {
      "has_mutton": "2020-03-30 01:23:30 +0530"
    },
    "done": true
  },
  "minecraft:recipes/building_blocks/purple_wool": {
    "criteria": {
      "has_white_wool": "2020-03-30 01:23:30 +0530"
    },
    "done": true
  },
  "minecraft:recipes/food/cooked_porkchop_from_campfire_cooking": {
    "criteria": {
      "has_porkchop": "2020-03-30 01:52:39 +0530"
    },
    "done": true
  },
  "minecraft:recipes/misc/pink_dye_from_red_white_dye": {
    "criteria": {
      "has_red_dye": "2020-03-30 02:11:55 +0530"
    },
    "done": true
  },
  "minecraft:recipes/tools/wooden_axe": {
    "criteria": {
      "has_stick": "2020-03-30 00:57:28 +0530"
    },
    "done": true
  },
  "minecraft:recipes/building_blocks/lime_wool": {
    "criteria": {
      "has_white_wool": "2020-03-30 01:23:30 +0530"
    },
    "done": true
  },
  "minecraft:recipes/redstone/lever": {
    "criteria": {
      "has_cobblestone": "2020-03-30 01:01:42 +0530"
    },
    "done": true
  },
  "minecraft:recipes/building_blocks/granite_stairs": {
    "criteria": {
      "has_granite": "2020-03-30 01:11:35 +0530"
    },
    "done": true
  },
  "minecraft:recipes/building_blocks/cobblestone_stairs_from_cobblestone_stonecutting": {
    "criteria": {
      "has_cobblestone": "2020-03-30 01:01:42 +0530"
    },
    "done": true
  },
  "minecraft:recipes/combat/iron_sword": {
    "criteria": {
      "has_iron_ingot": "2020-03-30 01:17:49 +0530"
    },
    "done": true
  },
  "minecraft:recipes/building_blocks/black_wool": {
    "criteria": {
      "has_white_wool": "2020-03-30 01:23:30 +0530"
    },
    "done": true
  },
  "minecraft:recipes/decorations/loom": {
    "criteria": {
      "has_string": "2020-03-30 02:11:55 +0530"
    },
    "done": true
  },
  "minecraft:recipes/building_blocks/polished_andesite_stairs_from_andesite_stonecutting": {
    "criteria": {
      "has_andesite": "2020-03-30 01:01:50 +0530"
    },
    "done": true
  },
  "minecraft:recipes/decorations/white_bed": {
    "criteria": {
      "has_white_wool": "2020-03-30 01:23:30 +0530"
    },
    "done": true
  },
  "minecraft:recipes/building_blocks/green_wool": {
    "criteria": {
      "has_white_wool": "2020-03-30 01:23:30 +0530"
    },
    "done": true
  },
  "minecraft:recipes/tools/iron_pickaxe": {
    "criteria": {
      "has_iron_ingot": "2020-03-30 01:17:49 +0530"
    },
    "done": true
  },
  "minecraft:recipes/building_blocks/diorite_stairs_from_diorite_stonecutting": {
    "criteria": {
      "has_diorite": "2020-03-30 01:04:44 +0530"
    },
    "done": true
  },
  "minecraft:recipes/building_blocks/brown_wool": {
    "criteria": {
      "has_white_wool": "2020-03-30 01:23:30 +0530"
    },
    "done": true
  },
  "minecraft:recipes/redstone/birch_pressure_plate": {
    "criteria": {
      "has_planks": "2020-03-30 02:15:40 +0530"
    },
    "done": true
  },
  "minecraft:recipes/decorations/campfire": {
    "criteria": {
      "has_stick": "2020-03-30 00:57:28 +0530"
    },
    "done": true
  },
  "minecraft:recipes/decorations/crafting_table": {
    "criteria": {
      "has_planks": "2020-03-30 01:01:16 +0530"
    },
    "done": true
  },
  "minecraft:recipes/building_blocks/magenta_wool": {
    "criteria": {
      "has_white_wool": "2020-03-30 01:23:30 +0530"
    },
    "done": true
  },
  "minecraft:recipes/food/bread": {
    "criteria": {
      "has_wheat": "2020-03-30 02:11:55 +0530"
    },
    "done": true
  },
  "minecraft:recipes/building_blocks/diorite_slab_from_diorite_stonecutting": {
    "criteria": {
      "has_diorite": "2020-03-30 01:04:44 +0530"
    },
    "done": true
  },
  "minecraft:recipes/decorations/ladder": {
    "criteria": {
      "has_stick": "2020-03-30 00:57:28 +0530"
    },
    "done": true
  },
  "minecraft:recipes/misc/iron_nugget": {
    "criteria": {
      "has_iron_ingot": "2020-03-30 01:17:49 +0530"
    },
    "done": true
  },
  "minecraft:recipes/building_blocks/dark_oak_slab": {
    "criteria": {
      "has_planks": "2020-03-30 02:11:55 +0530"
    },
    "done": true
  },
  "minecraft:recipes/decorations/chest": {
    "criteria": {
      "has_lots_of_items": "2020-03-30 01:01:50 +0530"
    },
    "done": true
  },
  "minecraft:recipes/building_blocks/iron_block": {
    "criteria": {
      "has_iron_ingot": "2020-03-30 01:17:49 +0530"
    },
    "done": true
  },
  "minecraft:recipes/redstone/birch_button": {
    "criteria": {
      "has_planks": "2020-03-30 02:15:40 +0530"
    },
    "done": true
  },
  "minecraft:recipes/decorations/painting": {
    "criteria": {
      "has_wool": "2020-03-30 01:23:30 +0530"
    },
    "done": true
  },
  "minecraft:recipes/tools/wooden_shovel": {
    "criteria": {
      "has_stick": "2020-03-30 00:57:28 +0530"
    },
    "done": true
  },
  "minecraft:recipes/decorations/torch": {
    "criteria": {
      "has_stone_pickaxe": "2020-03-30 01:02:57 +0530"
    },
    "done": true
  },
  "minecraft:recipes/misc/gold_ingot_from_blasting": {
    "criteria": {
      "has_gold_ore": "2020-03-30 01:11:35 +0530"
    },
    "done": true
  },
  "minecraft:recipes/redstone/dark_oak_button": {
    "criteria": {
      "has_planks": "2020-03-30 02:11:55 +0530"
    },
    "done": true
  },
  "minecraft:recipes/building_blocks/cyan_wool": {
    "criteria": {
      "has_white_wool": "2020-03-30 01:23:30 +0530"
    },
    "done": true
  },
  "minecraft:recipes/tools/shears": {
    "criteria": {
      "has_iron_ingot": "2020-03-30 01:17:49 +0530"
    },
    "done": true
  },
  "minecraft:recipes/decorations/red_carpet_from_white_carpet": {
    "criteria": {
      "has_red_dye": "2020-03-30 02:11:55 +0530"
    },
    "done": true
  },
  "minecraft:recipes/misc/stick": {
    "criteria": {
      "has_the_recipe": "2020-03-30 01:00:48 +0530"
    },
    "done": true
  },
  "minecraft:recipes/building_blocks/andesite_slab_from_andesite_stonecutting": {
    "criteria": {
      "has_andesite": "2020-03-30 01:01:50 +0530"
    },
    "done": true
  },
  "minecraft:recipes/combat/arrow": {
    "criteria": {
      "has_feather": "2020-03-30 01:23:01 +0530"
    },
    "done": true
  },
  "minecraft:recipes/building_blocks/coal_block": {
    "criteria": {
      "has_coal": "2020-03-30 01:01:54 +0530"
    },
    "done": true
  },
  "minecraft:recipes/misc/iron_ingot_from_blasting": {
    "criteria": {
      "has_iron_ore": "2020-03-30 01:10:20 +0530"
    },
    "done": true
  },
  "minecraft:recipes/misc/gold_ingot": {
    "criteria": {
      "has_gold_ore": "2020-03-30 01:11:35 +0530"
    },
    "done": true
  },
  "minecraft:recipes/transportation/spruce_boat": {
    "criteria": {
      "in_water": "2020-03-30 00:59:08 +0530"
    },
    "done": true
  },
  "minecraft:story/deflect_arrow": {
    "criteria": {
      "deflected_projectile": "2020-03-30 16:04:25 +0530"
    },
    "done": true
  },
  "minecraft:recipes/building_blocks/light_blue_wool": {
    "criteria": {
      "has_white_wool": "2020-03-30 01:23:30 +0530"
    },
    "done": true
  },
  "minecraft:recipes/combat/wooden_sword": {
    "criteria": {
      "has_stick": "2020-03-30 00:57:28 +0530"
    },
    "done": true
  },
  "minecraft:recipes/tools/stone_shovel": {
    "criteria": {
      "has_cobblestone": "2020-03-30 01:01:42 +0530"
    },
    "done": true
  },
  "minecraft:recipes/building_blocks/oak_planks": {
    "criteria": {
      "has_log": "2020-03-30 00:59:48 +0530"
    },
    "done": true
  },
  "minecraft:recipes/building_blocks/diorite_stairs": {
    "criteria": {
      "has_diorite": "2020-03-30 01:04:44 +0530"
    },
    "done": true
  },
  "minecraft:recipes/food/cake": {
    "criteria": {
      "has_egg": "2020-03-30 01:09:13 +0530"
    },
    "done": true
  },
  "minecraft:recipes/building_blocks/granite_slab_from_granite_stonecutting": {
    "criteria": {
      "has_granite": "2020-03-30 01:11:35 +0530"
    },
    "done": true
  },
  "minecraft:recipes/building_blocks/gray_wool": {
    "criteria": {
      "has_white_wool": "2020-03-30 01:23:30 +0530"
    },
    "done": true
  },
  "minecraft:recipes/building_blocks/polished_granite_from_granite_stonecutting": {
    "criteria": {
      "has_granite": "2020-03-30 01:11:35 +0530"
    },
    "done": true
  },
  "minecraft:recipes/combat/iron_leggings": {
    "criteria": {
      "has_iron_ingot": "2020-03-30 01:17:49 +0530"
    },
    "done": true
  },
  "minecraft:recipes/redstone/dark_oak_door": {
    "criteria": {
      "has_planks": "2020-03-30 02:11:55 +0530"
    },
    "done": true
  },
  "minecraft:recipes/tools/iron_axe": {
    "criteria": {
      "has_iron_ingot": "2020-03-30 01:17:49 +0530"
    },
    "done": true
  },
  "minecraft:husbandry/balanced_diet": {
    "criteria": {
      "cooked_mutton": "2020-03-30 01:25:33 +0530",
      "mutton": "2020-03-30 01:49:51 +0530"
    },
    "done": false
  },
  "minecraft:recipes/tools/wooden_hoe": {
    "criteria": {
      "has_stick": "2020-03-30 00:57:28 +0530"
    },
    "done": true
  },
  "minecraft:recipes/building_blocks/andesite": {
    "criteria": {
      "has_stone": "2020-03-30 01:04:44 +0530"
    },
    "done": true
  },
  "minecraft:recipes/combat/shield": {
    "criteria": {
      "has_iron_ingot": "2020-03-30 01:17:49 +0530"
    },
    "done": true
  },
  "minecraft:recipes/building_blocks/cobblestone_slab": {
    "criteria": {
      "has_cobblestone": "2020-03-30 01:01:42 +0530"
    },
    "done": true
  },
  "minecraft:recipes/misc/bucket": {
    "criteria": {
      "has_iron_ingot": "2020-03-30 01:17:49 +0530"
    },
    "done": true
  },
  "minecraft:recipes/redstone/tripwire_hook": {
    "criteria": {
      "has_string": "2020-03-30 02:11:55 +0530"
    },
    "done": true
  },
  "minecraft:recipes/redstone/oak_pressure_plate": {
    "criteria": {
      "has_planks": "2020-03-30 01:01:16 +0530"
    },
    "done": true
  },
  "minecraft:recipes/combat/iron_boots": {
    "criteria": {
      "has_iron_ingot": "2020-03-30 01:17:49 +0530"
    },
    "done": true
  },
  "minecraft:recipes/misc/bone_meal": {
    "criteria": {
      "has_bone": "2020-03-30 01:46:56 +0530"
    },
    "done": true
  },
  "minecraft:recipes/building_blocks/cobblestone_stairs": {
    "criteria": {
      "has_cobblestone": "2020-03-30 01:01:42 +0530"
    },
    "done": true
  },
  "minecraft:recipes/building_blocks/diorite_slab": {
    "criteria": {
      "has_diorite": "2020-03-30 01:04:44 +0530"
    },
    "done": true
  },
  "minecraft:recipes/redstone/hopper": {
    "criteria": {
      "has_iron_ingot": "2020-03-30 01:17:49 +0530"
    },
    "done": true
  },
  "minecraft:recipes/building_blocks/birch_slab": {
    "criteria": {
      "has_planks": "2020-03-30 02:15:40 +0530"
    },
    "done": true
  },
  "minecraft:story/iron_tools": {
    "criteria": {
      "iron_pickaxe": "2020-03-30 01:11:35 +0530"
    },
    "done": true
  },
  "minecraft:recipes/decorations/granite_wall": {
    "criteria": {
      "has_granite": "2020-03-30 01:11:35 +0530"
    },
    "done": true
  },
  "minecraft:recipes/decorations/cartography_table": {
    "criteria": {
      "has_string": "2020-03-30 02:11:55 +0530"
    },
    "done": true
  },
  "minecraft:recipes/building_blocks/oak_wood": {
    "criteria": {
      "has_log": "2020-03-30 00:59:48 +0530"
    },
    "done": true
  },
  "minecraft:recipes/redstone/birch_fence_gate": {
    "criteria": {
      "has_planks": "2020-03-30 02:15:40 +0530"
    },
    "done": true
  },
  "minecraft:recipes/decorations/white_banner": {
    "criteria": {
      "has_white_wool": "2020-03-30 01:23:30 +0530"
    },
    "done": true
  },
  "minecraft:recipes/combat/crossbow": {
    "criteria": {
      "has_stick": "2020-03-30 00:57:28 +0530"
    },
    "done": true
  },
  "minecraft:recipes/combat/iron_chestplate": {
    "criteria": {
      "has_iron_ingot": "2020-03-30 01:17:49 +0530"
    },
    "done": true
  },
  "minecraft:recipes/building_blocks/yellow_wool": {
    "criteria": {
      "has_white_wool": "2020-03-30 01:23:30 +0530"
    },
    "done": true
  },
  "minecraft:recipes/redstone/dark_oak_trapdoor": {
    "criteria": {
      "has_planks": "2020-03-30 02:11:55 +0530"
    },
    "done": true
  },
  "minecraft:recipes/decorations/oak_sign": {
    "criteria": {
      "has_oak_planks": "2020-03-30 01:01:16 +0530"
    },
    "done": true
  },
  "minecraft:recipes/food/cooked_porkchop_from_smoking": {
    "criteria": {
      "has_porkchop": "2020-03-30 01:52:39 +0530"
    },
    "done": true
  },
  "minecraft:recipes/redstone/oak_trapdoor": {
    "criteria": {
      "has_planks": "2020-03-30 01:01:16 +0530"
    },
    "done": true
  },
  "minecraft:recipes/building_blocks/polished_diorite_from_diorite_stonecutting": {
    "criteria": {
      "has_diorite": "2020-03-30 01:04:44 +0530"
    },
    "done": true
  },
  "minecraft:recipes/building_blocks/granite_stairs_from_granite_stonecutting": {
    "criteria": {
      "has_granite": "2020-03-30 01:11:35 +0530"
    },
    "done": true
  },
  "minecraft:recipes/building_blocks/hay_block": {
    "criteria": {
      "has_wheat": "2020-03-30 02:11:55 +0530"
    },
    "done": true
  },
  "minecraft:recipes/combat/iron_helmet": {
    "criteria": {
      "has_iron_ingot": "2020-03-30 01:17:49 +0530"
    },
    "done": true
  },
  "minecraft:recipes/combat/bow": {
    "criteria": {
      "has_string": "2020-03-30 02:11:55 +0530"
    },
    "done": true
  },
  "minecraft:recipes/misc/magenta_dye_from_blue_red_white_dye": {
    "criteria": {
      "has_rose_red": "2020-03-30 02:11:55 +0530"
    },
    "done": true
  },
  "minecraft:recipes/misc/iron_nugget_from_blasting": {
    "criteria": {
      "has_iron_pickaxe": "2020-03-30 01:11:35 +0530"
    },
    "done": true
  },
  "minecraft:recipes/redstone/oak_fence_gate": {
    "criteria": {
      "has_planks": "2020-03-30 01:01:16 +0530"
    },
    "done": true
  },
  "minecraft:recipes/food/cooked_chicken_from_smoking": {
    "criteria": {
      "has_chicken": "2020-03-30 01:23:01 +0530"
    },
    "done": true
  },
  "minecraft:recipes/misc/composter": {
    "criteria": {
      "has_wood_slab": "2020-03-30 02:11:55 +0530"
    },
    "done": true
  },
  "minecraft:adventure/kill_a_mob": {
    "criteria": {
      "minecraft:zombie": "2020-03-30 01:08:23 +0530"
    },
    "done": true
  },
  "minecraft:recipes/redstone/oak_button": {
    "criteria": {
      "has_planks": "2020-03-30 01:01:16 +0530"
    },
    "done": true
  },
  "minecraft:recipes/building_blocks/andesite_stairs_from_andesite_stonecutting": {
    "criteria": {
      "has_andesite": "2020-03-30 01:01:50 +0530"
    },
    "done": true
  },
  "minecraft:recipes/decorations/iron_bars": {
    "criteria": {
      "has_iron_ingot": "2020-03-30 01:17:49 +0530"
    },
    "done": true
  },
  "minecraft:recipes/decorations/diorite_wall_from_diorite_stonecutting": {
    "criteria": {
      "has_diorite": "2020-03-30 01:04:44 +0530"
    },
    "done": true
  },
  "minecraft:recipes/misc/iron_ingot": {
    "criteria": {
      "has_iron_ore": "2020-03-30 01:10:20 +0530"
    },
    "done": true
  },
  "minecraft:recipes/misc/magenta_dye_from_blue_red_pink": {
    "criteria": {
      "has_red_dye": "2020-03-30 02:11:55 +0530"
    },
    "done": true
  },
  "minecraft:recipes/decorations/diorite_wall": {
    "criteria": {
      "has_diorite": "2020-03-30 01:04:44 +0530"
    },
    "done": true
  },
  "minecraft:recipes/building_blocks/blue_wool": {
    "criteria": {
      "has_white_wool": "2020-03-30 01:23:30 +0530"
    },
    "done": true
  },
  "minecraft:story/obtain_armor": {
    "criteria": {
      "iron_leggings": "2020-03-30 01:33:10 +0530"
    },
    "done": true
  },
  "minecraft:story/mine_stone": {
    "criteria": {
      "get_stone": "2020-03-30 01:01:42 +0530"
    },
    "done": true
  },
  "minecraft:recipes/building_blocks/stone": {
    "criteria": {
      "has_cobblestone": "2020-03-30 01:01:42 +0530"
    },
    "done": true
  },
  "minecraft:recipes/building_blocks/polished_andesite": {
    "criteria": {
      "has_stone": "2020-03-30 01:01:50 +0530"
    },
    "done": true
  },
  "minecraft:recipes/redstone/dark_oak_pressure_plate": {
    "criteria": {
      "has_planks": "2020-03-30 02:11:55 +0530"
    },
    "done": true
  },
  "minecraft:recipes/decorations/furnace": {
    "criteria": {
      "has_cobblestone": "2020-03-30 01:01:42 +0530"
    },
    "done": true
  },
  "minecraft:recipes/transportation/minecart": {
    "criteria": {
      "has_iron_ingot": "2020-03-30 01:17:49 +0530"
    },
    "done": true
  },
  "minecraft:adventure/adventuring_time": {
    "criteria": {
      "minecraft:forest": "2020-03-30 00:54:09 +0530",
      "minecraft:beach": "2020-03-30 02:18:50 +0530",
      "minecraft:wooded_hills": "2020-03-30 01:30:51 +0530",
      "minecraft:plains": "2020-03-30 00:54:58 +0530"
    },
    "done": false
  },
  "minecraft:recipes/redstone/iron_door": {
    "criteria": {
      "has_iron_ingot": "2020-03-30 01:17:49 +0530"
    },
    "done": true
  },
  "minecraft:recipes/misc/charcoal": {
    "criteria": {
      "has_log": "2020-03-30 00:59:48 +0530"
    },
    "done": true
  },
  "minecraft:recipes/building_blocks/andesite_stairs": {
    "criteria": {
      "has_andesite": "2020-03-30 01:01:50 +0530"
    },
    "done": true
  },
  "minecraft:adventure/sleep_in_bed": {
    "criteria": {
      "slept_in_bed": "2020-03-30 02:10:50 +0530"
    },
    "done": true
  },
  "minecraft:recipes/building_blocks/orange_wool": {
    "criteria": {
      "has_white_wool": "2020-03-30 01:23:30 +0530"
    },
    "done": true
  },
  "minecraft:recipes/tools/wooden_pickaxe": {
    "criteria": {
      "has_stick": "2020-03-30 00:57:28 +0530"
    },
    "done": true
  },
  "minecraft:recipes/tools/iron_hoe": {
    "criteria": {
      "has_iron_ingot": "2020-03-30 01:17:49 +0530"
    },
    "done": true
  },
  "minecraft:recipes/building_blocks/cobblestone_slab_from_cobblestone_stonecutting": {
    "criteria": {
      "has_cobblestone": "2020-03-30 01:01:42 +0530"
    },
    "done": true
  },
  "minecraft:husbandry/root": {
    "criteria": {
      "consumed_item": "2020-03-30 01:25:33 +0530"
    },
    "done": true
  },
  "minecraft:recipes/transportation/birch_boat": {
    "criteria": {
      "in_water": "2020-03-30 00:59:08 +0530"
    },
    "done": true
  },
  "minecraft:recipes/combat/stone_sword": {
    "criteria": {
      "has_cobblestone": "2020-03-30 01:01:42 +0530"
    },
    "done": true
  },
  "minecraft:recipes/building_blocks/oak_stairs": {
    "criteria": {
      "has_planks": "2020-03-30 01:01:16 +0530"
    },
    "done": true
  },
  "minecraft:recipes/decorations/barrel": {
    "criteria": {
      "has_planks": "2020-03-30 01:01:16 +0530"
    },
    "done": true
  },
  "minecraft:recipes/decorations/cobblestone_wall": {
    "criteria": {
      "has_cobblestone": "2020-03-30 01:01:42 +0530"
    },
    "done": true
  },
  "minecraft:recipes/building_blocks/polished_andesite_slab_from_andesite_stonecutting": {
    "criteria": {
      "has_andesite": "2020-03-30 01:01:50 +0530"
    },
    "done": true
  },
  "minecraft:recipes/building_blocks/polished_granite_slab_from_granite_stonecutting": {
    "criteria": {
      "has_granite": "2020-03-30 01:11:35 +0530"
    },
    "done": true
  },
  "minecraft:recipes/building_blocks/polished_andesite_from_andesite_stonecutting": {
    "criteria": {
      "has_andesite": "2020-03-30 01:01:50 +0530"
    },
    "done": true
  },
  "minecraft:recipes/transportation/acacia_boat": {
    "criteria": {
      "in_water": "2020-03-30 00:59:08 +0530"
    },
    "done": true
  },
  "minecraft:recipes/tools/iron_shovel": {
    "criteria": {
      "has_iron_ingot": "2020-03-30 01:17:49 +0530"
    },
    "done": true
  },
  "minecraft:recipes/tools/stone_pickaxe": {
    "criteria": {
      "has_cobblestone": "2020-03-30 01:01:42 +0530"
    },
    "done": true
  },
  "minecraft:recipes/redstone/iron_trapdoor": {
    "criteria": {
      "has_iron_ingot": "2020-03-30 01:17:49 +0530"
    },
    "done": true
  },
  "minecraft:recipes/decorations/smithing_table": {
    "criteria": {
      "has_iron_ingot": "2020-03-30 01:17:49 +0530"
    },
    "done": true
  },
  "minecraft:recipes/redstone/oak_door": {
    "criteria": {
      "has_planks": "2020-03-30 01:01:16 +0530"
    },
    "done": true
  },
  "minecraft:recipes/decorations/birch_sign": {
    "criteria": {
      "has_birch_planks": "2020-03-30 02:15:40 +0530"
    },
    "done": true
  },
  "minecraft:adventure/root": {
    "criteria": {
      "killed_something": "2020-03-30 01:08:23 +0530"
    },
    "done": true
  },
  "minecraft:recipes/misc/purple_dye": {
    "criteria": {
      "has_red_dye": "2020-03-30 02:11:55 +0530"
    },
    "done": true
  },
  "minecraft:recipes/transportation/jungle_boat": {
    "criteria": {
      "in_water": "2020-03-30 00:59:08 +0530"
    },
    "done": true
  },
  "minecraft:recipes/decorations/cobblestone_wall_from_cobblestone_stonecutting": {
    "criteria": {
      "has_cobblestone": "2020-03-30 01:01:42 +0530"
    },
    "done": true
  },
  "minecraft:recipes/building_blocks/birch_stairs": {
    "criteria": {
      "has_planks": "2020-03-30 02:15:40 +0530"
    },
    "done": true
  },
  "minecraft:recipes/redstone/heavy_weighted_pressure_plate": {
    "criteria": {
      "has_iron_ingot": "2020-03-30 01:17:49 +0530"
    },
    "done": true
  },
  "minecraft:recipes/tools/stone_hoe": {
    "criteria": {
      "has_cobblestone": "2020-03-30 01:01:42 +0530"
    },
    "done": true
  },
  "minecraft:recipes/building_blocks/white_wool_from_string": {
    "criteria": {
      "has_string": "2020-03-30 02:11:55 +0530"
    },
    "done": true
  },
  "minecraft:recipes/transportation/dark_oak_boat": {
    "criteria": {
      "in_water": "2020-03-30 00:59:08 +0530"
    },
    "done": true
  },
  "minecraft:recipes/decorations/andesite_wall_from_andesite_stonecutting": {
    "criteria": {
      "has_andesite": "2020-03-30 01:01:50 +0530"
    },
    "done": true
  },
  "minecraft:recipes/building_blocks/pink_wool": {
    "criteria": {
      "has_white_wool": "2020-03-30 01:23:30 +0530"
    },
    "done": true
  },
  "minecraft:adventure/kill_all_mobs": {
    "criteria": {
      "minecraft:skeleton": "2020-03-30 16:04:26 +0530",
      "minecraft:zombie": "2020-03-30 01:08:23 +0530"
    },
    "done": false
  },
  "minecraft:recipes/building_blocks/dark_oak_stairs": {
    "criteria": {
      "has_planks": "2020-03-30 02:11:55 +0530"
    },
    "done": true
  },
  "minecraft:recipes/building_blocks/polished_granite": {
    "criteria": {
      "has_stone": "2020-03-30 01:11:35 +0530"
    },
    "done": true
  },
  "minecraft:recipes/building_blocks/granite_slab": {
    "criteria": {
      "has_granite": "2020-03-30 01:11:35 +0530"
    },
    "done": true
  },
  "minecraft:recipes/redstone/birch_trapdoor": {
    "criteria": {
      "has_planks": "2020-03-30 02:15:40 +0530"
    },
    "done": true
  },
  "minecraft:recipes/decorations/lantern": {
    "criteria": {
      "has_iron_ingot": "2020-03-30 01:17:49 +0530"
    },
    "done": true
  },
  "minecraft:recipes/decorations/white_carpet": {
    "criteria": {
      "has_white_wool": "2020-03-30 01:23:30 +0530"
    },
    "done": true
  },
  "minecraft:recipes/food/cooked_chicken_from_campfire_cooking": {
    "criteria": {
      "has_chicken": "2020-03-30 01:23:01 +0530"
    },
    "done": true
  },
  "minecraft:recipes/decorations/dark_oak_sign": {
    "criteria": {
      "has_dark_oak_planks": "2020-03-30 02:11:55 +0530"
    },
    "done": true
  },
  "minecraft:recipes/redstone/dark_oak_fence_gate": {
    "criteria": {
      "has_planks": "2020-03-30 02:11:55 +0530"
    },
    "done": true
  },
  "minecraft:recipes/misc/iron_nugget_from_smelting": {
    "criteria": {
      "has_iron_pickaxe": "2020-03-30 01:11:35 +0530"
    },
    "done": true
  },
  "minecraft:recipes/food/cooked_mutton_from_smoking": {
    "criteria": {
      "has_mutton": "2020-03-30 01:23:30 +0530"
    },
    "done": true
  },
  "minecraft:recipes/redstone/birch_door": {
    "criteria": {
      "has_planks": "2020-03-30 02:15:40 +0530"
    },
    "done": true
  },
  "minecraft:recipes/decorations/granite_wall_from_granite_stonecutting": {
    "criteria": {
      "has_granite": "2020-03-30 01:11:35 +0530"
    },
    "done": true
  },
  "minecraft:recipes/decorations/dark_oak_fence": {
    "criteria": {
      "has_planks": "2020-03-30 02:11:55 +0530"
    },
    "done": true
  },
  "minecraft:recipes/building_blocks/polished_diorite": {
    "criteria": {
      "has_stone": "2020-03-30 01:04:44 +0530"
    },
    "done": true
  },
  "minecraft:story/upgrade_tools": {
    "criteria": {
      "stone_pickaxe": "2020-03-30 01:02:57 +0530"
    },
    "done": true
  },
  "minecraft:recipes/decorations/andesite_wall": {
    "criteria": {
      "has_andesite": "2020-03-30 01:01:50 +0530"
    },
    "done": true
  },
  "minecraft:recipes/building_blocks/polished_granite_stairs_from_granite_stonecutting": {
    "criteria": {
      "has_granite": "2020-03-30 01:11:35 +0530"
    },
    "done": true
  },
  "minecraft:recipes/building_blocks/light_gray_wool": {
    "criteria": {
      "has_white_wool": "2020-03-30 01:23:30 +0530"
    },
    "done": true
  },
  "minecraft:recipes/building_blocks/andesite_slab": {
    "criteria": {
      "has_andesite": "2020-03-30 01:01:50 +0530"
    },
    "done": true
  },
  "minecraft:recipes/food/cooked_chicken": {
    "criteria": {
      "has_chicken": "2020-03-30 01:23:01 +0530"
    },
    "done": true
  },
  "minecraft:recipes/decorations/oak_fence": {
    "criteria": {
      "has_planks": "2020-03-30 01:01:16 +0530"
    },
    "done": true
  },
  "minecraft:recipes/building_blocks/red_wool": {
    "criteria": {
      "has_white_wool": "2020-03-30 01:23:30 +0530"
    },
    "done": true
  },
  "minecraft:recipes/decorations/red_stained_glass_pane_from_glass_pane": {
    "criteria": {
      "has_red_dye": "2020-03-30 02:11:55 +0530"
    },
    "done": true
  },
  "minecraft:recipes/transportation/oak_boat": {
    "criteria": {
      "in_water": "2020-03-30 00:59:08 +0530"
    },
    "done": true
  },
  "minecraft:recipes/misc/orange_dye_from_red_yellow": {
    "criteria": {
      "has_red_dye": "2020-03-30 02:11:55 +0530"
    },
    "done": true
  },
  "minecraft:story/smelt_iron": {
    "criteria": {
      "iron": "2020-03-30 01:17:49 +0530"
    },
    "done": true
  },
  "minecraft:recipes/tools/stone_axe": {
    "criteria": {
      "has_cobblestone": "2020-03-30 01:01:42 +0530"
    },
    "done": true
  },
  "minecraft:recipes/food/cooked_mutton": {
    "criteria": {
      "has_mutton": "2020-03-30 01:23:30 +0530"
    },
    "done": true
  },
  "minecraft:recipes/decorations/birch_fence": {
    "criteria": {
      "has_planks": "2020-03-30 02:15:40 +0530"
    },
    "done": true
  },
  "minecraft:recipes/food/cooked_porkchop": {
    "criteria": {
      "has_porkchop": "2020-03-30 01:52:39 +0530"
    },
    "done": true
  },
  "minecraft:recipes/building_blocks/oak_slab": {
    "criteria": {
      "has_planks": "2020-03-30 01:01:16 +0530"
    },
    "done": true
  },
  "DataVersion": 2230
}